rastgelekelime/__init__.py
rastgelekelime/index.py
rastgelekelime/data/wordList.json
rastgelekelime-10.0.0.dist-info/licenses/LICENSE
rastgelekelime-10.0.0.dist-info/METADATA
rastgelekelime-10.0.0.dist-info/WHEEL
rastgelekelime-10.0.0.dist-info/top_level.txt
rastgelekelime-10.0.0.dist-info/RECORD
