Metadata-Version: 2.4
Name: rastgelekelime
Version: 10.0.0
Summary: Bir yada daha fazla Türkçe kelime çıktısı alın.
Home-page: https://github.com/EnesKeremAYDIN/pip-rastgelekelime
Author: Enes Kerem AYDIN
Classifier: Programming Language :: Python :: 3
Classifier: License :: OSI Approved :: MIT License
Classifier: Operating System :: OS Independent
Requires-Python: >=3.6
License-File: LICENSE
Dynamic: author
Dynamic: classifier
Dynamic: home-page
Dynamic: license-file
Dynamic: requires-python
Dynamic: summary
